[
{
    "pk": 4,
    "fields": {
        "name": "Dayuuuum",
        "scenery": null,
        "pet": 1,
        "date_created": "2015-05-05T12:21:25Z",
        "level": 10,
        "inventory": 18
    },
    "model": "tracktivityPetsWebsite.collectedpet"
},
{
    "pk": 5,
    "fields": {
        "name": "Melv",
        "scenery": 2,
        "pet": 3,
        "date_created": "2015-04-25T13:43:21Z",
        "level": 10,
        "inventory": 20
    },
    "model": "tracktivityPetsWebsite.collectedpet"
},
{
    "pk": 7,
    "fields": {
        "name": "YoloMan",
        "scenery": null,
        "pet": 4,
        "date_created": "2015-05-13T10:28:12Z",
        "level": 6,
        "inventory": 32
    },
    "model": "tracktivityPetsWebsite.collectedpet"
},
{
    "pk": 8,
    "fields": {
        "name": "Sheldz",
        "scenery": null,
        "pet": 2,
        "date_created": "2015-05-14T14:41:09.768Z",
        "level": 1,
        "inventory": 36
    },
    "model": "tracktivityPetsWebsite.collectedpet"
},
{
    "pk": 9,
    "fields": {
        "name": "Loser",
        "scenery": null,
        "pet": 3,
        "date_created": "2015-05-14T04:58:07.217Z",
        "level": 1,
        "inventory": 39
    },
    "model": "tracktivityPetsWebsite.collectedpet"
},
{
    "pk": 10,
    "fields": {
        "name": "YoloMAn",
        "scenery": null,
        "pet": 1,
        "date_created": "2015-05-15T10:08:19.926Z",
        "level": 1,
        "inventory": 44
    },
    "model": "tracktivityPetsWebsite.collectedpet"
},
{
    "pk": 11,
    "fields": {
        "name": "Redic",
        "scenery": null,
        "pet": 4,
        "date_created": "2015-05-15T01:14:56.855Z",
        "level": 1,
        "inventory": 45
    },
    "model": "tracktivityPetsWebsite.collectedpet"
},
{
    "pk": 12,
    "fields": {
        "name": "Curly Fries",
        "scenery": null,
        "pet": 1,
        "date_created": "2015-05-15T02:40:04Z",
        "level": 10,
        "inventory": 47
    },
    "model": "tracktivityPetsWebsite.collectedpet"
},
{
    "pk": 13,
    "fields": {
        "name": "turtlecopter",
        "scenery": null,
        "pet": 2,
        "date_created": "2015-05-15T03:12:50.684Z",
        "level": 1,
        "inventory": 48
    },
    "model": "tracktivityPetsWebsite.collectedpet"
},
{
    "pk": 14,
    "fields": {
        "name": "Snailton",
        "scenery": null,
        "pet": 3,
        "date_created": "2015-05-15T05:36:33.091Z",
        "level": 1,
        "inventory": 22
    },
    "model": "tracktivityPetsWebsite.collectedpet"
},
{
    "pk": 15,
    "fields": {
        "name": "rabis",
        "scenery": null,
        "pet": 4,
        "date_created": "2015-05-15T05:46:47.059Z",
        "level": 1,
        "inventory": 23
    },
    "model": "tracktivityPetsWebsite.collectedpet"
},
{
    "pk": 16,
    "fields": {
        "name": "tuckcoptor",
        "scenery": null,
        "pet": 2,
        "date_created": "2015-05-15T13:15:32.008Z",
        "level": 10,
        "inventory": 49
    },
    "model": "tracktivityPetsWebsite.collectedpet"
},
{
    "pk": 17,
    "fields": {
        "name": "Little Pig",
        "scenery": null,
        "pet": 1,
        "date_created": "2015-05-18T09:01:47.942Z",
        "level": 10,
        "inventory": 51
    },
    "model": "tracktivityPetsWebsite.collectedpet"
},
{
    "pk": 18,
    "fields": {
        "name": "",
        "scenery": null,
        "pet": 4,
        "date_created": "2015-05-20T16:11:35.549Z",
        "level": 1,
        "inventory": 53
    },
    "model": "tracktivityPetsWebsite.collectedpet"
},
{
    "pk": 19,
    "fields": {
        "name": "test",
        "scenery": null,
        "pet": 1,
        "date_created": "2015-05-21T04:24:03.280Z",
        "level": 1,
        "inventory": 24
    },
    "model": "tracktivityPetsWebsite.collectedpet"
},
{
    "pk": 20,
    "fields": {
        "name": "Pickle Bunny",
        "scenery": null,
        "pet": 4,
        "date_created": "2015-05-21T06:48:50.401Z",
        "level": 1,
        "inventory": 21
    },
    "model": "tracktivityPetsWebsite.collectedpet"
},
{
    "pk": 21,
    "fields": {
        "name": "Shelly",
        "scenery": null,
        "pet": 2,
        "date_created": "2015-05-24T23:43:57.247Z",
        "level": 1,
        "inventory": 56
    },
    "model": "tracktivityPetsWebsite.collectedpet"
},
{
    "pk": 22,
    "fields": {
        "name": "Shelly",
        "scenery": null,
        "pet": 2,
        "date_created": "2015-05-25T00:37:55.092Z",
        "level": 1,
        "inventory": 57
    },
    "model": "tracktivityPetsWebsite.collectedpet"
},
{
    "pk": 23,
    "fields": {
        "name": "John",
        "scenery": null,
        "pet": 2,
        "date_created": "2015-05-27T11:28:50.125Z",
        "level": 4,
        "inventory": 58
    },
    "model": "tracktivityPetsWebsite.collectedpet"
},
{
    "pk": 24,
    "fields": {
        "name": "Fred",
        "scenery": null,
        "pet": 3,
        "date_created": "2015-05-27T11:52:33.251Z",
        "level": 3,
        "inventory": 60
    },
    "model": "tracktivityPetsWebsite.collectedpet"
},
{
    "pk": 25,
    "fields": {
        "name": "Lachlan",
        "scenery": null,
        "pet": 1,
        "date_created": "2015-05-27T11:53:11.200Z",
        "level": 4,
        "inventory": 59
    },
    "model": "tracktivityPetsWebsite.collectedpet"
},
{
    "pk": 26,
    "fields": {
        "name": "Sir Oinksalot",
        "scenery": null,
        "pet": 1,
        "date_created": "2015-05-31T06:24:09.236Z",
        "level": 1,
        "inventory": 61
    },
    "model": "tracktivityPetsWebsite.collectedpet"
},
{
    "pk": 27,
    "fields": {
        "name": "nj",
        "scenery": null,
        "pet": 1,
        "date_created": "2015-07-14T10:00:09.943Z",
        "level": 1,
        "inventory": 62
    },
    "model": "tracktivityPetsWebsite.collectedpet"
},
{
    "pk": 28,
    "fields": {
        "name": "e",
        "scenery": null,
        "pet": 2,
        "date_created": "2015-07-14T14:55:11.533Z",
        "level": 1,
        "inventory": 63
    },
    "model": "tracktivityPetsWebsite.collectedpet"
},
{
    "pk": 29,
    "fields": {
        "name": "Turtz",
        "scenery": null,
        "pet": 2,
        "date_created": "2015-08-01T14:56:58.970Z",
        "level": 5,
        "inventory": 20
    },
    "model": "tracktivityPetsWebsite.collectedpet"
}
]
